{"matchData":{"statisticTypes":["redCards","yellowCards","fouls","foulsSuffered","slidingTackles","slidingTacklesCompleted","goalsConceded","shots","shotsOnGoal","passesCompleted","interceptions","offsides","goals","ownGoals","assists","passes","freeKicks","penalties","corners","throwIns","keeperSaves","goalKicks","possession","distanceCovered","keeperSavesCaught"],"matchInfo":{"type":"Public Match","startTime":1585759398,"endTime":1585761051,"periods":2,"lastPeriodName":"SECOND HALF"},"teams":[{"matchTotal":{"name":"Excel","side":"home","isMix":true,"statistics":[0,1,1,1,4,1,3,8,8,135,61,3,3,0,2,199,1,0,3,1,1,2,711,48371,1]},"matchPeriods":[{"period":1,"periodName":"FIRST HALF","announcedInjuryTimeSeconds":60,"actualInjuryTimeSeconds":60,"statistics":[0,1,1,0,2,0,1,7,7,69,29,3,3,0,2,95,0,0,2,0,1,1,343,24389,1]},{"period":2,"periodName":"SECOND HALF","announcedInjuryTimeSeconds":60,"actualInjuryTimeSeconds":60,"statistics":[0,0,0,1,2,1,2,1,1,66,32,0,0,0,0,104,1,0,1,1,0,1,368,24002,0]}]},{"matchTotal":{"name":"Dishwashers","side":"away","isMix":true,"statistics":[0,1,1,1,9,0,3,5,4,88,51,0,3,0,1,148,4,0,0,7,5,3,497,47621,3]},"matchPeriods":[{"period":1,"periodName":"FIRST HALF","announcedInjuryTimeSeconds":60,"actualInjuryTimeSeconds":60,"statistics":[0,0,0,1,5,0,3,2,2,45,20,0,1,0,0,74,4,0,0,3,4,2,265,23825,2]},{"period":2,"periodName":"SECOND HALF","announcedInjuryTimeSeconds":60,"actualInjuryTimeSeconds":60,"statistics":[0,1,1,0,4,0,0,3,2,43,31,0,2,0,1,74,0,0,0,4,1,1,232,23816,1]}]}],"players":[{"info":{"steamId":"STEAM_0:1:112826015","name":"tesro"},"matchPeriodData":[{"info":{"startSecond":0,"endSecond":2760,"team":"home","position":"LW"},"statistics":[0,0,0,0,0,0,0,1,1,4,1,1,1,0,0,6,0,0,1,0,0,0,18,3551,0]},{"info":{"startSecond":2700,"endSecond":5460,"team":"home","position":"LW"},"statistics":[0,0,0,0,0,0,0,1,1,5,1,0,0,0,0,12,0,0,1,0,0,0,61,3540,0]}]},{"info":{"steamId":"STEAM_0:1:18712036","name":"vader"},"matchPeriodData":[{"info":{"startSecond":0,"endSecond":2760,"team":"home","position":"LB"},"statistics":[0,0,0,0,1,0,0,0,0,14,7,0,0,0,0,15,0,0,0,0,0,0,40,3391,0]},{"info":{"startSecond":2700,"endSecond":5460,"team":"home","position":"LB"},"statistics":[0,0,0,0,0,0,0,0,0,13,10,0,0,0,0,17,0,0,0,0,0,0,49,3377,0]}]},{"info":{"steamId":"STEAM_0:0:6789707","name":"Paulo Dybala"},"matchPeriodData":[{"info":{"startSecond":0,"endSecond":2760,"team":"home","position":"CM"},"statistics":[0,0,0,0,0,0,0,2,2,7,1,0,1,0,0,8,0,0,0,0,0,0,30,3496,0]},{"info":{"startSecond":2700,"endSecond":5460,"team":"home","position":"CM"},"statistics":[0,0,0,0,0,0,0,0,0,8,3,0,0,0,0,12,0,0,0,0,0,0,35,3585,0]}]},{"info":{"steamId":"STEAM_0:1:11766677","name":"arizona"},"matchPeriodData":[{"info":{"startSecond":0,"endSecond":2760,"team":"home","position":"RB"},"statistics":[0,1,1,0,1,0,0,0,0,10,6,0,0,0,0,16,0,0,0,0,0,0,63,3389,0]},{"info":{"startSecond":2700,"endSecond":2700,"team":"home","position":"RB"},"statistics":[0,0,0,0,0,0,0,0,0,0,0,0,0,0,0,0,0,0,0,0,0,0,0,0,0]},{"info":{"startSecond":2718,"endSecond":5460,"team":"home","position":"RB"},"statistics":[0,0,0,0,0,0,0,0,0,7,5,0,0,0,0,11,0,0,0,1,0,0,35,2989,0]}]},{"info":{"steamId":"STEAM_0:1:49179806","name":"Ragnar"},"matchPeriodData":[{"info":{"startSecond":0,"endSecond":2760,"team":"home","position":"CB"},"statistics":[0,0,0,0,0,0,0,0,0,12,9,0,0,0,0,15,0,0,0,0,0,0,57,3110,0]},{"info":{"startSecond":2700,"endSecond":5460,"team":"home","position":"CB"},"statistics":[0,0,0,0,1,0,0,0,0,8,9,0,0,0,0,17,0,0,0,0,0,0,69,3069,0]}]},{"info":{"steamId":"STEAM_0:1:51906464","name":"Guus"},"matchPeriodData":[{"info":{"startSecond":0,"endSecond":2760,"team":"home","position":"RW"},"statistics":[0,0,0,0,0,0,0,1,1,4,1,2,0,0,0,10,0,0,1,0,0,0,38,3405,0]},{"info":{"startSecond":2700,"endSecond":5460,"team":"home","position":"RW"},"statistics":[0,0,0,1,1,1,0,0,0,11,1,0,0,0,0,14,1,0,0,0,0,0,40,3511,0]}]},{"info":{"steamId":"STEAM_0:1:4460440","name":"SOUFLEE"},"matchPeriodData":[{"info":{"startSecond":0,"endSecond":2760,"team":"home","position":"CF"},"statistics":[0,0,0,0,0,0,0,3,3,13,3,0,1,0,2,16,0,0,0,0,0,0,72,3715,0]},{"info":{"startSecond":2700,"endSecond":3924,"team":"home","position":"CF"},"statistics":[0,0,0,0,0,0,0,0,0,8,2,0,0,0,0,10,0,0,0,0,0,0,31,1651,0]},{"info":{"startSecond":3924,"endSecond":5460,"team":"home","position":"CF"},"statistics":[0,0,0,0,0,0,0,0,0,2,0,0,0,0,0,3,0,0,0,0,0,0,19,1875,0]}]},{"info":{"steamId":"STEAM_0:0:2023144","name":"Josh"},"matchPeriodData":[{"info":{"startSecond":0,"endSecond":2760,"team":"away","position":"CF"},"statistics":[0,0,0,0,1,0,0,1,1,5,2,0,0,0,0,15,0,0,0,1,0,0,42,3462,0]},{"info":{"startSecond":2700,"endSecond":5460,"team":"away","position":"CF"},"statistics":[0,0,0,0,0,0,0,0,0,8,1,0,0,0,0,12,0,0,0,0,0,0,39,3598,0]}]},{"info":{"steamId":"STEAM_0:1:533276115","name":"U"},"matchPeriodData":[{"info":{"startSecond":0,"endSecond":2760,"team":"away","position":"LB"},"statistics":[0,0,0,0,0,0,0,0,0,7,0,0,0,0,0,7,0,0,0,2,0,0,16,3028,0]},{"info":{"startSecond":2700,"endSecond":5460,"team":"away","position":"LB"},"statistics":[0,0,0,0,0,0,0,0,0,7,4,0,0,0,0,10,0,0,0,1,0,0,25,3063,0]}]},{"info":{"steamId":"STEAM_0:0:238482663","name":"F"},"matchPeriodData":[{"info":{"startSecond":0,"endSecond":2,"team":"away","position":"GK"},"statistics":[0,0,0,0,0,0,0,0,0,0,0,0,0,0,0,0,0,0,0,0,0,0,0,0,0]},{"info":{"startSecond":2,"endSecond":88,"team":"home","position":"GK"},"statistics":[0,0,0,0,0,0,0,0,0,1,0,0,0,0,0,1,0,0,0,0,0,0,2,11,0]},{"info":{"startSecond":88,"endSecond":199,"team":"away","position":"GK"},"statistics":[0,0,0,0,0,0,0,0,0,1,0,0,0,0,0,2,0,0,0,0,0,1,5,43,0]},{"info":{"startSecond":199,"endSecond":229,"team":"home","position":"GK"},"statistics":[0,0,0,0,0,0,0,0,0,0,0,0,0,0,0,0,0,0,0,0,0,0,0,2,0]},{"info":{"startSecond":229,"endSecond":376,"team":"away","position":"GK"},"statistics":[0,0,0,0,0,0,0,0,0,0,0,0,0,0,0,0,0,0,0,0,0,0,0,6,0]},{"info":{"startSecond":376,"endSecond":388,"team":"home","position":"GK"},"statistics":[0,0,0,0,0,0,0,0,0,0,0,0,0,0,0,0,0,0,0,0,0,0,0,2,0]},{"info":{"startSecond":388,"endSecond":435,"team":"away","position":"GK"},"statistics":[0,0,0,0,0,0,0,0,0,0,0,0,0,0,0,0,0,0,0,0,0,0,0,2,0]},{"info":{"startSecond":435,"endSecond":490,"team":"home","position":"GK"},"statistics":[0,0,0,0,0,0,0,0,0,1,0,0,0,0,0,1,0,0,0,0,0,0,6,44,0]},{"info":{"startSecond":490,"endSecond":505,"team":"away","position":"GK"},"statistics":[0,0,0,0,0,0,0,0,0,0,0,0,0,0,0,0,0,0,0,0,0,0,0,3,0]},{"info":{"startSecond":505,"endSecond":545,"team":"home","position":"GK"},"statistics":[0,0,0,0,0,0,0,0,0,0,0,0,0,0,0,0,0,0,0,0,0,0,0,3,0]},{"info":{"startSecond":545,"endSecond":650,"team":"away","position":"GK"},"statistics":[0,0,0,0,0,0,1,0,0,0,0,0,0,0,0,0,0,0,0,0,0,0,0,6,0]},{"info":{"startSecond":650,"endSecond":723,"team":"home","position":"GK"},"statistics":[0,0,0,0,0,0,0,0,0,0,1,0,0,0,0,1,0,0,0,0,0,0,1,16,0]},{"info":{"startSecond":723,"endSecond":802,"team":"away","position":"GK"},"statistics":[0,0,0,0,0,0,0,0,0,1,0,0,0,0,0,1,0,0,0,0,2,0,4,39,0]},{"info":{"startSecond":802,"endSecond":838,"team":"home","position":"GK"},"statistics":[0,0,0,0,0,0,0,0,0,0,0,0,0,0,0,0,0,0,0,0,0,0,0,3,0]},{"info":{"startSecond":838,"endSecond":885,"team":"away","position":"GK"},"statistics":[0,0,0,0,0,0,0,0,0,0,0,0,0,0,0,0,0,0,0,0,0,0,0,16,0]},{"info":{"startSecond":885,"endSecond":1027,"team":"home","position":"GK"},"statistics":[0,0,0,0,0,0,0,0,0,0,0,0,0,0,0,0,0,0,0,0,0,0,0,5,0]},{"info":{"startSecond":1027,"endSecond":1331,"team":"away","position":"GK"},"statistics":[0,0,0,0,0,0,0,0,0,2,0,0,0,0,0,3,0,0,0,0,2,0,4,94,2]},{"info":{"startSecond":1331,"endSecond":1543,"team":"home","position":"GK"},"statistics":[0,0,0,0,0,0,0,0,0,1,0,0,0,0,0,2,0,0,0,0,1,0,2,50,1]},{"info":{"startSecond":1543,"endSecond":1725,"team":"away","position":"GK"},"statistics":[0,0,0,0,0,0,1,0,0,1,1,0,0,0,0,2,0,0,0,0,0,0,7,77,0]},{"info":{"startSecond":1725,"endSecond":1728,"team":"home","position":"GK"},"statistics":[0,0,0,0,0,0,0,0,0,0,0,0,0,0,0,0,0,0,0,0,0,0,0,2,0]},{"info":{"startSecond":1728,"endSecond":1772,"team":"away","position":"GK"},"statistics":[0,0,0,0,0,0,0,0,0,0,0,0,0,0,0,0,0,0,0,0,0,0,0,4,0]},{"info":{"startSecond":1772,"endSecond":1894,"team":"home","position":"GK"},"statistics":[0,0,0,0,0,0,0,0,0,1,0,0,0,0,0,1,0,0,0,0,0,0,2,55,0]},{"info":{"startSecond":1894,"endSecond":1959,"team":"away","position":"GK"},"statistics":[0,0,0,0,0,0,1,0,0,0,0,0,0,0,0,0,0,0,0,0,0,0,0,8,0]},{"info":{"startSecond":1959,"endSecond":1985,"team":"home","position":"GK"},"statistics":[0,0,0,0,0,0,0,0,0,0,0,0,0,0,0,0,0,0,0,0,0,0,0,4,0]},{"info":{"startSecond":1985,"endSecond":1998,"team":"away","position":"GK"},"statistics":[0,0,0,0,0,0,0,0,0,0,0,0,0,0,0,0,0,0,0,0,0,0,0,3,0]},{"info":{"startSecond":1998,"endSecond":2096,"team":"home","position":"GK"},"statistics":[0,0,0,0,0,0,0,0,0,1,0,0,0,0,0,1,0,0,0,0,0,0,1,46,0]},{"info":{"startSecond":2096,"endSecond":2139,"team":"away","position":"GK"},"statistics":[0,0,0,0,0,0,0,0,0,0,0,0,0,0,0,0,0,0,0,0,0,0,0,4,0]},{"info":{"startSecond":2139,"endSecond":2362,"team":"home","position":"GK"},"statistics":[0,0,0,0,0,0,0,0,0,0,0,0,0,0,0,0,0,0,0,0,0,0,0,11,0]},{"info":{"startSecond":2362,"endSecond":2429,"team":"away","position":"GK"},"statistics":[0,0,0,0,0,0,0,0,0,1,0,0,0,0,0,1,0,0,0,0,0,1,2,21,0]},{"info":{"startSecond":2429,"endSecond":2461,"team":"home","position":"GK"},"statistics":[0,0,0,0,0,0,0,0,0,0,0,0,0,0,0,0,0,0,0,0,0,0,0,29,0]},{"info":{"startSecond":2461,"endSecond":2482,"team":"away","position":"GK"},"statistics":[0,0,0,0,0,0,0,0,0,0,1,0,0,0,0,0,0,0,0,0,0,0,0,32,0]},{"info":{"startSecond":2482,"endSecond":2534,"team":"home","position":"GK"},"statistics":[0,0,0,0,0,0,0,0,0,0,0,0,0,0,0,2,0,0,0,0,0,1,2,27,0]},{"info":{"startSecond":2534,"endSecond":2597,"team":"away","position":"GK"},"statistics":[0,0,0,0,0,0,0,0,0,0,0,0,0,0,0,0,0,0,0,0,0,0,0,6,0]},{"info":{"startSecond":2597,"endSecond":2628,"team":"home","position":"GK"},"statistics":[0,0,0,0,0,0,0,0,0,0,0,0,0,0,0,0,0,0,0,0,0,0,0,2,0]},{"info":{"startSecond":2628,"endSecond":2675,"team":"away","position":"GK"},"statistics":[0,0,0,0,0,0,0,0,0,0,0,0,0,0,0,0,0,0,0,0,0,0,0,3,0]},{"info":{"startSecond":2675,"endSecond":2758,"team":"home","position":"GK"},"statistics":[0,0,0,0,0,0,1,0,0,0,0,0,0,0,0,0,0,0,0,0,0,0,0,10,0]},{"info":{"startSecond":2758,"endSecond":2760,"team":"away","position":"GK"},"statistics":[0,0,0,0,0,0,0,0,0,0,0,0,0,0,0,0,0,0,0,0,0,0,0,0,0]},{"info":{"startSecond":2700,"endSecond":2787,"team":"away","position":"GK"},"statistics":[0,0,0,0,0,0,0,0,0,0,0,0,0,0,0,0,0,0,0,0,0,1,2,10,0]},{"info":{"startSecond":2787,"endSecond":2963,"team":"home","position":"GK"},"statistics":[0,0,0,0,0,0,1,0,0,0,0,0,0,0,0,1,0,0,0,0,0,0,0,39,0]},{"info":{"startSecond":2963,"endSecond":3103,"team":"away","position":"GK"},"statistics":[0,0,0,0,0,0,0,0,0,1,0,0,0,0,0,1,0,0,0,0,0,0,2,56,0]},{"info":{"startSecond":3103,"endSecond":3226,"team":"home","position":"GK"},"statistics":[0,0,0,0,0,0,0,0,0,0,0,0,0,0,0,0,0,0,0,0,0,0,0,5,0]},{"info":{"startSecond":3226,"endSecond":3305,"team":"away","position":"GK"},"statistics":[0,0,0,0,0,0,0,0,0,1,0,0,0,0,0,1,0,0,0,0,1,0,1,27,1]},{"info":{"startSecond":3305,"endSecond":3348,"team":"home","position":"GK"},"statistics":[0,0,0,0,0,0,0,0,0,0,0,0,0,0,0,1,0,0,0,0,0,0,6,40,0]},{"info":{"startSecond":3348,"endSecond":3369,"team":"away","position":"GK"},"statistics":[0,0,0,0,0,0,0,0,0,0,0,0,0,0,0,0,0,0,0,0,0,0,0,4,0]},{"info":{"startSecond":3369,"endSecond":3398,"team":"home","position":"GK"},"statistics":[0,0,0,0,0,0,0,0,0,0,0,0,0,0,0,0,0,0,0,0,0,0,0,3,0]},{"info":{"startSecond":3398,"endSecond":3402,"team":"away","position":"GK"},"statistics":[0,0,0,0,0,0,0,0,0,0,0,0,0,0,0,0,0,0,0,0,0,0,0,0,0]},{"info":{"startSecond":3402,"endSecond":3536,"team":"home","position":"GK"},"statistics":[0,0,0,0,0,0,0,0,0,1,0,0,0,0,0,1,0,0,0,0,0,0,2,28,0]},{"info":{"startSecond":3536,"endSecond":3592,"team":"away","position":"GK"},"statistics":[0,0,0,0,0,0,0,0,0,0,0,0,0,0,0,0,0,0,0,0,0,0,0,3,0]},{"info":{"startSecond":3592,"endSecond":3668,"team":"home","position":"GK"},"statistics":[0,0,0,0,0,0,0,0,0,0,0,0,0,0,0,0,0,0,0,0,0,0,0,21,0]},{"info":{"startSecond":3668,"endSecond":3768,"team":"away","position":"GK"},"statistics":[0,0,0,0,0,0,0,0,0,0,0,0,0,0,0,0,0,0,0,0,0,0,0,37,0]},{"info":{"startSecond":3768,"endSecond":3798,"team":"home","position":"GK"},"statistics":[0,0,0,0,0,0,0,0,0,1,1,0,0,0,0,1,0,0,0,0,0,0,1,48,0]},{"info":{"startSecond":3798,"endSecond":3949,"team":"away","position":"GK"},"statistics":[0,0,0,0,0,0,0,0,0,0,0,0,0,0,0,0,0,0,0,0,0,0,0,26,0]},{"info":{"startSecond":3949,"endSecond":4051,"team":"home","position":"GK"},"statistics":[0,0,0,0,0,0,0,0,0,0,0,0,0,0,0,0,0,0,0,0,0,0,0,2,0]},{"info":{"startSecond":4051,"endSecond":4141,"team":"away","position":"GK"},"statistics":[0,0,0,0,0,0,0,0,0,0,0,0,0,0,0,0,0,0,0,0,0,0,0,13,0]},{"info":{"startSecond":4141,"endSecond":4194,"team":"home","position":"GK"},"statistics":[0,0,0,0,0,0,0,0,0,0,0,0,0,0,0,0,0,0,0,0,0,0,0,1,0]},{"info":{"startSecond":4194,"endSecond":4269,"team":"away","position":"GK"},"statistics":[0,0,0,0,0,0,0,0,0,0,0,0,0,0,0,0,0,0,0,0,0,0,0,4,0]},{"info":{"startSecond":4269,"endSecond":4341,"team":"home","position":"GK"},"statistics":[0,0,0,0,0,0,1,0,0,0,0,0,0,0,0,0,0,0,0,0,0,0,0,14,0]},{"info":{"startSecond":4341,"endSecond":4345,"team":"away","position":"GK"},"statistics":[0,0,0,0,0,0,0,0,0,0,0,0,0,0,0,0,0,0,0,0,0,0,0,0,0]},{"info":{"startSecond":4345,"endSecond":4418,"team":"home","position":"GK"},"statistics":[0,0,0,0,0,0,0,0,0,0,0,0,0,0,0,0,0,0,0,0,0,0,0,13,0]},{"info":{"startSecond":4418,"endSecond":4441,"team":"away","position":"GK"},"statistics":[0,0,0,0,0,0,0,0,0,0,1,0,0,0,0,0,0,0,0,0,0,0,0,32,0]},{"info":{"startSecond":4441,"endSecond":4585,"team":"home","position":"GK"},"statistics":[0,0,0,0,0,0,0,0,0,1,0,0,0,0,0,2,0,0,0,0,0,0,11,90,0]},{"info":{"startSecond":4585,"endSecond":4598,"team":"away","position":"GK"},"statistics":[0,0,0,0,0,0,0,0,0,0,0,0,0,0,0,0,0,0,0,0,0,0,0,0,0]},{"info":{"startSecond":4598,"endSecond":4688,"team":"home","position":"GK"},"statistics":[0,0,0,0,0,0,0,0,0,1,0,0,0,0,0,1,0,0,0,0,0,1,1,48,0]},{"info":{"startSecond":4688,"endSecond":4900,"team":"away","position":"GK"},"statistics":[0,0,0,0,0,0,0,0,0,0,0,0,0,0,0,0,0,0,0,0,0,0,0,15,0]},{"info":{"startSecond":4900,"endSecond":5096,"team":"home","position":"GK"},"statistics":[0,0,0,0,0,0,0,0,0,0,0,0,0,0,0,0,0,0,0,0,0,0,0,3,0]},{"info":{"startSecond":5096,"endSecond":5132,"team":"away","position":"GK"},"statistics":[0,0,0,0,0,0,0,0,0,0,1,0,0,0,0,0,0,0,0,0,0,0,0,53,0]},{"info":{"startSecond":5132,"endSecond":5217,"team":"home","position":"GK"},"statistics":[0,0,0,0,0,0,0,0,0,0,0,0,0,0,0,1,0,0,0,0,0,0,0,32,0]},{"info":{"startSecond":5217,"endSecond":5249,"team":"away","position":"GK"},"statistics":[0,0,0,0,0,0,0,0,0,1,1,0,0,0,0,1,0,0,0,0,0,0,1,34,0]},{"info":{"startSecond":5249,"endSecond":5460,"team":"home","position":"GK"},"statistics":[0,0,0,0,0,0,0,0,0,0,0,0,0,0,0,0,0,0,0,0,0,0,0,10,0]}]},{"info":{"steamId":"STEAM_0:0:100576502","name":"Dipson"},"matchPeriodData":[]},{"info":{"steamId":"STEAM_0:0:18410733","name":"dead weight"},"matchPeriodData":[{"info":{"startSecond":0,"endSecond":2760,"team":"away","position":"RB"},"statistics":[0,0,0,0,1,0,0,0,0,5,3,0,0,0,0,6,0,0,0,0,0,0,15,3232,0]},{"info":{"startSecond":2700,"endSecond":3924,"team":"away","position":"RB"},"statistics":[0,0,0,0,0,0,0,0,0,4,5,0,0,0,0,6,0,0,0,0,0,0,17,1402,0]},{"info":{"startSecond":3924,"endSecond":5460,"team":"away","position":"RB"},"statistics":[0,0,0,0,1,0,0,0,0,1,1,0,0,0,1,1,0,0,0,0,0,0,7,1708,0]}]},{"info":{"steamId":"STEAM_0:0:120385187","name":"lemon"},"matchPeriodData":[{"info":{"startSecond":0,"endSecond":2760,"team":"away","position":"LW"},"statistics":[0,0,0,1,3,0,0,1,1,3,1,0,1,0,0,7,1,0,0,0,0,0,35,3333,0]},{"info":{"startSecond":2700,"endSecond":5460,"team":"away","position":"LW"},"statistics":[0,0,0,0,2,0,0,2,2,7,3,0,2,0,0,11,0,0,0,1,0,0,39,3317,0]}]},{"info":{"steamId":"STEAM_0:1:4373127","name":"DaapDaap"},"matchPeriodData":[{"info":{"startSecond":0,"endSecond":2760,"team":"away","position":"CM"},"statistics":[0,0,0,0,0,0,0,0,0,7,3,0,0,0,0,11,1,0,0,0,0,0,49,3558,0]},{"info":{"startSecond":2700,"endSecond":4293,"team":"away","position":"CM"},"statistics":[0,0,0,0,0,0,0,0,0,3,1,0,0,0,0,9,0,0,0,2,0,0,24,2037,0]},{"info":{"startSecond":4293,"endSecond":5460,"team":"away","position":"CB"},"statistics":[0,0,0,0,0,0,0,0,0,3,3,0,0,0,0,5,0,0,0,0,0,0,5,1317,0]}]},{"info":{"steamId":"STEAM_0:0:458951889","name":"Sorry"},"matchPeriodData":[{"info":{"startSecond":0,"endSecond":2760,"team":"away","position":"RW"},"statistics":[0,0,0,0,0,0,0,0,0,5,0,0,0,0,0,7,1,0,0,0,0,0,46,3422,0]},{"info":{"startSecond":2700,"endSecond":5460,"team":"away","position":"RW"},"statistics":[0,0,0,0,0,0,0,1,0,1,2,0,0,0,0,4,0,0,0,0,0,0,28,3517,0]}]},{"info":{"steamId":"STEAM_0:0:134661940","name":"flazy ;j"},"matchPeriodData":[{"info":{"startSecond":0,"endSecond":2760,"team":"away","position":"CB"},"statistics":[0,0,0,0,0,0,0,0,0,7,9,0,0,0,0,12,1,0,0,0,0,0,35,3419,0]},{"info":{"startSecond":2700,"endSecond":4293,"team":"away","position":"CB"},"statistics":[0,0,0,0,0,0,0,0,0,3,4,0,0,0,0,6,0,0,0,0,0,0,17,2001,0]},{"info":{"startSecond":4293,"endSecond":5460,"team":"away","position":"CM"},"statistics":[0,1,1,0,1,0,0,0,0,3,4,0,0,0,0,7,0,0,0,0,0,0,19,1533,0]}]},{"info":{"steamId":"STEAM_0:0:18205610","name":"BigBoyBelow"},"matchPeriodData":[]},{"info":{"steamId":"STEAM_0:1:78210451","name":"Davich"},"matchPeriodData":[]},{"info":{"steamId":"STEAM_0:0:504990385","name":"-VirUs`"},"matchPeriodData":[]},{"info":{"steamId":"STEAM_0:0:3033630","name":"Draggy"},"matchPeriodData":[]}],"matchEvents":[{"second":571,"event":"GOAL","period":"FIRST HALF","team":"home","player1SteamId":"STEAM_0:1:112826015","player2SteamId":"STEAM_0:1:4460440"},{"second":571,"event":"CELEBRATION","period":"FIRST HALF","team":"home","player1SteamId":"STEAM_0:1:112826015","player2SteamId":""},{"second":768,"event":"SAVE","period":"FIRST HALF","team":"away","player1SteamId":"STEAM_0:0:238482663","player2SteamId":"STEAM_0:1:4460440"},{"second":789,"event":"SAVE","period":"FIRST HALF","team":"away","player1SteamId":"STEAM_0:0:238482663","player2SteamId":"STEAM_0:0:6789707"},{"second":1067,"event":"SAVE","period":"FIRST HALF","team":"away","player1SteamId":"STEAM_0:0:238482663","player2SteamId":"STEAM_0:1:4460440"},{"second":1302,"event":"SAVE","period":"FIRST HALF","team":"away","player1SteamId":"STEAM_0:0:238482663","player2SteamId":"STEAM_0:1:51906464"},{"second":1466,"event":"SAVE","period":"FIRST HALF","team":"home","player1SteamId":"STEAM_0:0:238482663","player2SteamId":"STEAM_0:0:2023144"},{"second":1725,"event":"GOAL","period":"FIRST HALF","team":"home","player1SteamId":"STEAM_0:1:4460440","player2SteamId":""},{"second":1725,"event":"CELEBRATION","period":"FIRST HALF","team":"home","player1SteamId":"STEAM_0:1:4460440","player2SteamId":""},{"second":1916,"event":"GOAL","period":"FIRST HALF","team":"home","player1SteamId":"STEAM_0:0:6789707","player2SteamId":"STEAM_0:1:4460440"},{"second":1916,"event":"CELEBRATION","period":"FIRST HALF","team":"home","player1SteamId":"STEAM_0:0:6789707","player2SteamId":""},{"second":2689,"event":"YELLOW CARD","period":"FIRST HALF","team":"home","player1SteamId":"STEAM_0:1:11766677","player2SteamId":""},{"second":2744,"event":"GOAL","period":"FIRST HALF","team":"away","player1SteamId":"STEAM_0:0:120385187","player2SteamId":""},{"second":2744,"event":"CELEBRATION","period":"FIRST HALF","team":"away","player1SteamId":"STEAM_0:0:120385187","player2SteamId":""},{"second":2821,"event":"GOAL","period":"SECOND HALF","team":"away","player1SteamId":"STEAM_0:0:120385187","player2SteamId":""},{"second":2821,"event":"CELEBRATION","period":"SECOND HALF","team":"away","player1SteamId":"STEAM_0:0:120385187","player2SteamId":""},{"second":3246,"event":"SAVE","period":"SECOND HALF","team":"away","player1SteamId":"STEAM_0:0:238482663","player2SteamId":"STEAM_0:1:112826015"},{"second":4293,"event":"GOAL","period":"SECOND HALF","team":"away","player1SteamId":"STEAM_0:0:120385187","player2SteamId":"STEAM_0:0:18410733"},{"second":4293,"event":"CELEBRATION","period":"SECOND HALF","team":"away","player1SteamId":"STEAM_0:0:120385187","player2SteamId":""},{"second":4579,"event":"YELLOW CARD","period":"SECOND HALF","team":"away","player1SteamId":"STEAM_0:0:134661940","player2SteamId":""},{"second":4660,"event":"MISS","period":"SECOND HALF","team":"away","player1SteamId":"STEAM_0:0:458951889","player2SteamId":""}]}}